shepherd_score/__init__.py
shepherd_score/alignment.py
shepherd_score/alignment_jax.py
shepherd_score/conformer_generation.py
shepherd_score/container.py
shepherd_score/extract_profiles.py
shepherd_score/generate_point_cloud.py
shepherd_score/objective.py
shepherd_score/visualize.py
shepherd_score/alignment_utils/__init__.py
shepherd_score/alignment_utils/pca.py
shepherd_score/alignment_utils/pca_jax.py
shepherd_score/alignment_utils/pca_np.py
shepherd_score/alignment_utils/se3.py
shepherd_score/alignment_utils/se3_jax.py
shepherd_score/alignment_utils/se3_np.py
shepherd_score/evaluations/__init__.py
shepherd_score/evaluations/docking/__init__.py
shepherd_score/evaluations/docking/docking.py
shepherd_score/evaluations/docking/pipelines.py
shepherd_score/evaluations/docking/targets.py
shepherd_score/evaluations/docking/pdbs/1iep.pdbqt
shepherd_score/evaluations/docking/pdbs/3eml.pdbqt
shepherd_score/evaluations/docking/pdbs/3ny8.pdbqt
shepherd_score/evaluations/docking/pdbs/4rlu.pdbqt
shepherd_score/evaluations/docking/pdbs/4unn.pdbqt
shepherd_score/evaluations/docking/pdbs/5mo4.pdbqt
shepherd_score/evaluations/docking/pdbs/7l11.pdbqt
shepherd_score/evaluations/docking/pdbs/README.md
shepherd_score/evaluations/evaluate/__init__.py
shepherd_score/evaluations/evaluate/_pipeline_eval_single.py
shepherd_score/evaluations/evaluate/evals.py
shepherd_score/evaluations/evaluate/pipelines.py
shepherd_score/evaluations/utils/__init__.py
shepherd_score/evaluations/utils/convert_data.py
shepherd_score/evaluations/utils/interactions.py
shepherd_score/pharm_utils/__init__.py
shepherd_score/pharm_utils/pharmacophore.py
shepherd_score/pharm_utils/pharmvec.py
shepherd_score/pharm_utils/smarts_features.fdef
shepherd_score/protonation/__init__.py
shepherd_score/protonation/chemaxon_utils.py
shepherd_score/protonation/molscrub_utils.py
shepherd_score/protonation/protonate.py
shepherd_score/score/__init__.py
shepherd_score/score/constants.py
shepherd_score/score/electrostatic_scoring.py
shepherd_score-1.2.0.dist-info/licenses/LICENSE
shepherd_score-1.2.0.dist-info/METADATA
shepherd_score-1.2.0.dist-info/WHEEL
shepherd_score-1.2.0.dist-info/top_level.txt
shepherd_score-1.2.0.dist-info/RECORD
