Metadata-Version: 2.4
Name: shepherd-score
Version: 1.2.0
Summary: 3D scoring functions used for evaluation of ShEPhERD
Author-email: Kento Abeywardane <kento@mit.edu>
License: MIT
Project-URL: Homepage, https://github.com/kentoabeywardane/shepherd-score
Project-URL: Repository, https://github.com/kentoabeywardane/shepherd-score
Project-URL: Documentation, https://shepherd-score.readthedocs.io
Project-URL: Bug Tracker, https://github.com/kentoabeywardane/shepherd-score/issues
Keywords: bioinformatics,molecular-modeling,3d-scoring,drug-discovery,chemistry,bioisosteres
Classifier: Development Status :: 4 - Beta
Classifier: Intended Audience :: Science/Research
Classifier: Topic :: Scientific/Engineering :: Bio-Informatics
Classifier: Topic :: Scientific/Engineering :: Chemistry
Classifier: Programming Language :: Python :: 3
Classifier: Programming Language :: Python :: 3.9
Classifier: Programming Language :: Python :: 3.10
Classifier: Programming Language :: Python :: 3.11
Classifier: Programming Language :: Python :: 3.12
Classifier: Operating System :: OS Independent
Classifier: License :: OSI Approved :: MIT License
Requires-Python: >=3.9
License-File: LICENSE
Requires-Dist: rdkit<2025.09.3,>=2023.03; python_version == "3.9"
Requires-Dist: rdkit>=2023.03; python_version >= "3.10"
Requires-Dist: torch>=1.12
Requires-Dist: open3d>=0.18
Requires-Dist: py3Dmol
Requires-Dist: numpy
Requires-Dist: pandas>=2.0
Requires-Dist: scipy>=1.10
Requires-Dist: molscrub
Provides-Extra: dev
Requires-Dist: pytest>=6.0; extra == "dev"
Requires-Dist: pytest-cov; extra == "dev"
Requires-Dist: ruff; extra == "dev"
Requires-Dist: mypy; extra == "dev"
Provides-Extra: docs
Requires-Dist: sphinx>=7.0; extra == "docs"
Requires-Dist: sphinx-book-theme>=1.0; extra == "docs"
Requires-Dist: sphinx-copybutton>=0.5; extra == "docs"
Requires-Dist: myst-nb>=1.0; extra == "docs"
Provides-Extra: jax
Requires-Dist: jax>=0.4.20; extra == "jax"
Requires-Dist: jaxlib>=0.4.20; extra == "jax"
Requires-Dist: optax>=0.2.0; extra == "jax"
Requires-Dist: scikit-learn>=1.3; extra == "jax"
Provides-Extra: docking
Requires-Dist: meeko; extra == "docking"
Requires-Dist: vina>=1.2.5; extra == "docking"
Requires-Dist: openbabel; extra == "docking"
Requires-Dist: prolif>=2.0.3; extra == "docking"
Requires-Dist: biopython<1.86,>=1.84; python_version == "3.9" and extra == "docking"
Requires-Dist: biopython>=1.84; python_version >= "3.10" and extra == "docking"
Provides-Extra: all
Requires-Dist: shepherd-score[dev,docking,docs,jax]; extra == "all"
Dynamic: license-file
